ADTCreate/ADT.py
ADTCreate/ADTSatisfiability.py
ADTCreate/ADTXML.py
ADTCreate/CompareADTerms.py
ADTCreate/GenerateADTerm.py
ADTCreate/MultisetList.py
ADTCreate-1.0.0rc5.dist-info/LICENSE
ADTCreate-1.0.0rc5.dist-info/METADATA
ADTCreate-1.0.0rc5.dist-info/WHEEL
ADTCreate-1.0.0rc5.dist-info/top_level.txt
ADTCreate-1.0.0rc5.dist-info/RECORD
