Metadata-Version: 2.1
Name: ADTCreate
Version: 1.0.0rc5
Summary: ADT Create provides a general method to create and customize Attack-Defense Trees (ADTs), allowing users to visualize and analyse security scenarios. A user is able to create and customize ADTs from scratch, upload/download ADTs in XML format, generate ADTerms based on ADTs, compare ADTerms to determine equivalence using an equivalence threshold using the Levenshtein Distance, determine satisfiability of an ADT and generate statistics of an ADT
Author-email: Jayme Hebinck <jayme.hebinck@live.nl>
Project-URL: Homepage, https://github.com/MainJay/ADTPythonLibrary/
Project-URL: Issues, https://github.com/MainJay/ADTPythonLibrary/issues
Classifier: Programming Language :: Python :: 3
Classifier: License :: OSI Approved :: MIT License
Classifier: Operating System :: OS Independent
Requires-Python: >=3.7
License-File: LICENSE
Requires-Dist: Levenshtein >=0.23.0
Requires-Dist: numpy >=1.21.6
